N2SNUserTools/__init__.py
N2SNUserTools/_version.py
N2SNUserTools/cli.py
N2SNUserTools/ldap.py
N2SNUserTools/unix.py
N2SNUserTools/utils.py
n2snusertools-0.3.10.dist-info/licenses/LICENSE
n2snusertools-0.3.10.dist-info/METADATA
n2snusertools-0.3.10.dist-info/WHEEL
n2snusertools-0.3.10.dist-info/entry_points.txt
n2snusertools-0.3.10.dist-info/top_level.txt
n2snusertools-0.3.10.dist-info/RECORD
