Metadata-Version: 2.4
Name: N2SNUserTools
Version: 0.3.10
Summary: User Manipulation Tools for Python
Home-page: https://github.com/NSLS-II/N2SNUserTools
Author: Brookhaven National Laboratory
Author-email: swilkins@bnl.gov
License: BSD (3-clause)
Classifier: Development Status :: 2 - Pre-Alpha
Classifier: Natural Language :: English
Classifier: Programming Language :: Python :: 3
Requires-Python: >=3.6
License-File: LICENSE
Requires-Dist: ldap3
Requires-Dist: prettytable
Requires-Dist: gssapi
Requires-Dist: pyyaml
Dynamic: author
Dynamic: author-email
Dynamic: classifier
Dynamic: description
Dynamic: home-page
Dynamic: license
Dynamic: license-file
Dynamic: requires-dist
Dynamic: requires-python
Dynamic: summary
